flask_sms/__init__.py
flask_sms/aliyun_send.py
Flask_SMS-0.0.24.dist-info/LICENSE
Flask_SMS-0.0.24.dist-info/METADATA
Flask_SMS-0.0.24.dist-info/WHEEL
Flask_SMS-0.0.24.dist-info/top_level.txt
Flask_SMS-0.0.24.dist-info/RECORD
