Metadata-Version: 2.1
Name: Flask-SMS
Version: 0.0.24
Summary: flask-sms
Home-page: UNKNOWN
Author: 浩
Author-email: 
License: MIT
Keywords: flask extension development sms
Platform: any
Classifier: Programming Language :: Python :: 3
License-File: LICENSE
Requires-Dist: Flask
Requires-Dist: alibabacloud-dysmsapi20170525 (==2.0.24)
Requires-Dist: redis
